DEPENDENCIES
INSTALL
LICENSE
README
ez_setup.py
setup.py
TestGen4Web_Python.egg-info/PKG-INFO
TestGen4Web_Python.egg-info/SOURCES.txt
TestGen4Web_Python.egg-info/SOURCES_maint.txt
TestGen4Web_Python.egg-info/dependency_links.txt
TestGen4Web_Python.egg-info/requires.txt
TestGen4Web_Python.egg-info/top_level.txt
bin/testgen-convert
testgen/__init__.py
testgen/handler.py
testgen/mechcode.py
testgen/mechunit.py
testgen/parser.py
testgen/twillcode.py
testgen/twillshell.py
testgen/twillunit.py
testgen/zopecode.py
testgen/zopeunit.py
tests/devserver.py
tests/httptestserver.py
tests/test_mechunit.py
tests/test_parser.py
tests/cgi-bin/printSubmitted.py
tests/cgi-bin/printYes.py
tests/forms/simpleSubmit.html
tests/forms/submitCheckboxesRadiosSelect.html
tests/forms/submitTextInput.html
tests/forms/submitTextInputWithFormID.html
tests/forms/submitTextInputWithFormName.html
tests/links/index.html
tests/links/link1.html
tests/links/link2.html
tests/links/link3.html
tests/links/link4.html
tests/links/linklist.html
tests/sessions/testSimpleLinks.xml
tests/sessions/testSimpleSubmit.xml
tests/sessions/testSubmitCheckboxesRadiosSelect.xml
tests/sessions/testSubmitTextInputWithFormID.xml
tests/sessions/testSubmitTextInputWithFormName.xml
tests/sessions/testTextInputSubmit.xml
