Metadata-Version: 1.0
Name: TestGen4Web-Python
Version: 0.2.1
Summary: A pure-python set of translators for TestGen4Web
Home-page: http://dev.zenoss.org/trac/wiki/TestGen4Web-Python
Author: Duncan McGreggor
Author-email: oubiwann@adytum.us
License: MIT License
Platform: UNKNOWN
Classifier: Development Status :: 4 - Beta
Classifier: Environment :: Web Environment :: Mozilla
Classifier: Intended Audience :: Developers
Classifier: License :: OSI Approved :: MIT License
Classifier: Natural Language :: English
Classifier: Operating System :: OS Independent
Classifier: Programming Language :: Python
Classifier: Topic :: Internet :: WWW/HTTP :: Browsers
Classifier: Topic :: Software Development :: Testing
Classifier: Topic :: Software Development :: User Interfaces
